tor_ip_rotator/__init__.py
tor_ip_rotator/middlewares.py
tor_ip_rotator/tor_controller.py
scrapy_tor_proxy_rotation-0.0.4.dist-info/LICENSE
scrapy_tor_proxy_rotation-0.0.4.dist-info/METADATA
scrapy_tor_proxy_rotation-0.0.4.dist-info/WHEEL
scrapy_tor_proxy_rotation-0.0.4.dist-info/top_level.txt
scrapy_tor_proxy_rotation-0.0.4.dist-info/RECORD
