Metadata-Version: 2.1
Name: scrapy-tor-proxy-rotation
Version: 0.0.4
Summary: IP Rotator for Scrapy via Tor
Home-page: https://github.com/elvesrodrigues/scrapy-tor-proxy-rotation
Author: Elves M. Rodrigues
Author-email: elvesmateusrodrigues@gmail.com
Classifier: Programming Language :: Python :: 3
Classifier: License :: OSI Approved :: MIT License
Classifier: Operating System :: Unix
Requires-Python: >=3.6
License-File: LICENSE
Requires-Dist: pysocks (==1.7.1)
Requires-Dist: requests (==2.23.0)
Requires-Dist: stem (==1.8.0)
